django_elasticsearch_dsl_celery/__init__.py
django_elasticsearch_dsl_celery-1.1.dist-info/METADATA
django_elasticsearch_dsl_celery-1.1.dist-info/WHEEL
django_elasticsearch_dsl_celery-1.1.dist-info/top_level.txt
django_elasticsearch_dsl_celery-1.1.dist-info/RECORD
